easybench/__init__.py
easybench/cli.py
easybench/core.py
easybench/decorator.py
easybench/notebook.py
easybench/py.typed
easybench/reporters.py
easybench/utils.py
easybench/visualization.py
easybench-0.1.36.dist-info/METADATA
easybench-0.1.36.dist-info/WHEEL
easybench-0.1.36.dist-info/entry_points.txt
easybench-0.1.36.dist-info/licenses/LICENSE
easybench-0.1.36.dist-info/RECORD
