Metadata-Version: 2.4
Name: easybench
Version: 0.1.36
Summary: A simple and easy-to-use Python benchmarking library
Project-URL: Homepage, https://github.com/smurak/easybench
Project-URL: Bug Tracker, https://github.com/smurak/easybench/issues
Project-URL: Documentation, https://easybench.readthedocs.io/
Author-email: smurak <smurak000@gmail.com>
License: The MIT License (MIT)
License-File: LICENSE
Classifier: License :: OSI Approved :: MIT License
Classifier: Operating System :: OS Independent
Classifier: Programming Language :: Python :: 3
Requires-Python: >=3.10
Requires-Dist: pydantic>=2.0.0
Requires-Dist: typing-extensions; python_version < '3.11'
Provides-Extra: all
Requires-Dist: matplotlib; extra == 'all'
Requires-Dist: pandas; extra == 'all'
Requires-Dist: seaborn; extra == 'all'
Requires-Dist: tqdm; extra == 'all'
Provides-Extra: dev
Requires-Dist: black; extra == 'dev'
Requires-Dist: ipython; extra == 'dev'
Requires-Dist: matplotlib; extra == 'dev'
Requires-Dist: mypy; extra == 'dev'
Requires-Dist: pandas; extra == 'dev'
Requires-Dist: pandas-stubs; extra == 'dev'
Requires-Dist: ruff; extra == 'dev'
Requires-Dist: seaborn; extra == 'dev'
Requires-Dist: tqdm; extra == 'dev'
Requires-Dist: types-seaborn; extra == 'dev'
Requires-Dist: types-tqdm; extra == 'dev'
Provides-Extra: docs
Requires-Dist: black; extra == 'docs'
Requires-Dist: mkdocs-material; extra == 'docs'
Requires-Dist: mkdocstrings[python]; extra == 'docs'
Provides-Extra: test
Requires-Dist: pytest; extra == 'test'
Requires-Dist: pytest-cov; extra == 'test'
